ari3d/__init__.py
ari3d/gui/__init__.py
ari3d/gui/ari3d.py
ari3d/gui/ari3d_logging.py
ari3d/gui/controller/__init__.py
ari3d/gui/controller/window_c.py
ari3d/gui/controller/io/__init__.py
ari3d/gui/controller/io/album_c.py
ari3d/gui/controller/io/help_c.py
ari3d/gui/controller/io/project_c.py
ari3d/gui/controller/io/view_c.py
ari3d/gui/controller/solutions/__init__.py
ari3d/gui/controller/solutions/extract_properties_c.py
ari3d/gui/controller/solutions/particleSeg_c.py
ari3d/gui/controller/solutions/streamlit_c.py
ari3d/gui/model/__init__.py
ari3d/gui/model/decorators.py
ari3d/gui/model/tasks.py
ari3d/gui/model/watcher.py
ari3d/gui/view/MainWindow_ui.py
ari3d/gui/view/__init__.py
ari3d/gui/view/io/__init__.py
ari3d/gui/view/io/file.py
ari3d/gui/view/solutions/__init__.py
ari3d/gui/view/solutions/export_properties_ui.py
ari3d/gui/view/solutions/particleSegWindow_ui.py
ari3d/gui/view/solutions/particleSegWindow_ui_advanced.py
ari3d/gui/view/solutions/streamlit_ui.py
ari3d/resources/__init__.py
ari3d/resources/default_values.py
ari3d/resources/parameters.yml
ari3d/resources/images/logo/__init__.py
ari3d/resources/images/logo/analysis_curve.png
ari3d/resources/images/logo/logo_b.png
ari3d/resources/images/logo/logo_w.png
ari3d/resources/images/logo/logo_w_xs.png
ari3d/resources/images/logo/particle1.png
ari3d/resources/images/logo/particle2.png
ari3d/resources/images/logo/particle3.png
ari3d/resources/images/logo/particle4.png
ari3d/resources/images/logo/particle5.png
ari3d/resources/images/logo/particle6.png
ari3d/resources/images/logo/particle7.png
ari3d/resources/images/logo/particle_analysis.png
ari3d/solutions/__init__.py
ari3d/solutions/data_viewer/solution.py
ari3d/solutions/data_viewer/streamlit_data_viewer.py
ari3d/solutions/property_extraction/io_op.py
ari3d/solutions/property_extraction/properties.py
ari3d/solutions/property_extraction/solution.py
ari3d/solutions/property_extraction/utils.py
ari3d/solutions/segmentation/solution.py
ari3d/utils/__init__.py
ari3d-0.1.5.dist-info/licenses/LICENSE
ari3d-0.1.5.dist-info/METADATA
ari3d-0.1.5.dist-info/WHEEL
ari3d-0.1.5.dist-info/entry_points.txt
ari3d-0.1.5.dist-info/top_level.txt
ari3d-0.1.5.dist-info/RECORD
