Metadata-Version: 2.4
Name: ari3d
Version: 0.1.5
Summary: Analyse Regions in 3D
Author-email: Jan Philipp Albrecht <j.p.albrecht@fu-berlin.de>, Jose Ricardo Assuncao Godinho <jragodinho@uma.es>
License-Expression: MIT
Project-URL: Repository, https://gitlab.com/ida-mdc/ari3d
Keywords: X-ray,imaging,data analysis
Classifier: Development Status :: 3 - Alpha
Classifier: Operating System :: MacOS :: MacOS X
Classifier: Operating System :: Microsoft :: Windows
Classifier: Operating System :: POSIX
Classifier: Programming Language :: Python :: 3.11
Classifier: Programming Language :: Python :: Implementation :: PyPy
Classifier: Topic :: Utilities
Requires-Python: ~=3.11
License-File: LICENSE
Requires-Dist: PyQt6==6.7.1
Requires-Dist: PyQt6-Qt6==6.7.1
Requires-Dist: pandas
Requires-Dist: pillow
Requires-Dist: numpy
Requires-Dist: napari
Requires-Dist: zarr==2.18.7
Requires-Dist: watchdog
Requires-Dist: joblib
Requires-Dist: album~=0.12
Requires-Dist: numcodecs==0.15.1
Requires-Dist: snakemake
Requires-Dist: pywin32>=303; platform_system == "Windows"
Dynamic: license-file
